building_data_utilities/README.md
building_data_utilities/__init__.py
building_data_utilities/chunk.py
building_data_utilities/common.py
building_data_utilities/geocode_addresses.py
building_data_utilities/geojson_helpers.py
building_data_utilities/normalize_address.py
building_data_utilities/open_street_map.py
building_data_utilities/shp_to_geojson.py
building_data_utilities/ubid.py
building_data_utilities/update_dataset_links.py
building_data_utilities/update_quadkeys.py
building_data_utilities-0.1.0.dist-info/METADATA
building_data_utilities-0.1.0.dist-info/WHEEL
building_data_utilities-0.1.0.dist-info/licenses/LICENSE.md
building_data_utilities-0.1.0.dist-info/RECORD
