Metadata-Version: 2.4
Name: building-data-utilities
Version: 0.1.0
Summary: Utilities for parsing and understanding building-related data to support covered building list development.
License-File: LICENSE.md
Author: Alex Swindler
Author-email: alex.swinder@nrel.gov
Requires-Python: >=3.9,<3.13
Classifier: Programming Language :: Python :: 3
Classifier: Programming Language :: Python :: 3.9
Classifier: Programming Language :: Python :: 3.10
Classifier: Programming Language :: Python :: 3.11
Classifier: Programming Language :: Python :: 3.12
Requires-Dist: buildingid-nrel (>=2.2.0,<3.0.0)
Requires-Dist: geopandas (>=1.0.1,<2.0.0)
Requires-Dist: geopy (>=2.4.1,<3.0.0)
Requires-Dist: mercantile (>=1.2.1,<2.0.0)
Requires-Dist: nominatim (>=0.1,<0.2)
Requires-Dist: python-dotenv (>=1.0.1,<2.0.0)
Requires-Dist: requests (>=2.32.5,<3.0.0)
Requires-Dist: setuptools (>=80.9.0,<81.0.0)
Requires-Dist: shapely (>=2.0.6,<3.0.0)
Requires-Dist: street-address (==0.4.0)
Requires-Dist: usaddress (==0.5.16)
